_main/__init__.py
_main/main.py
_main/main.sh
_main/main_tmp.sh
_main/_base_structure/.dockerignore
_main/_base_structure/.env.example
_main/_base_structure/.gitignore
_main/_base_structure/Dockerfile
_main/_base_structure/LICENSE
_main/_base_structure/Makefile
_main/_base_structure/README.md
_main/_base_structure/docker-compose.yml
_main/_base_structure/main.py
_main/_base_structure/requirements.txt
_main/_base_structure/common/__init__.py
_main/_base_structure/common/flask.py
_main/_base_structure/common/response.py
_main/_base_structure/common/time_now.py
_main/_base_structure/common/validate_username.py
_main/_base_structure/common/__pycache__/__init__.cpython-310.pyc
_main/_base_structure/common/__pycache__/flask.cpython-310.pyc
_main/_base_structure/common/__pycache__/time_now.cpython-310.pyc
_main/_base_structure/common/__pycache__/validate_username.cpython-310.pyc
_main/_base_structure/domain/__init__.py
_main/_base_structure/domain/example.py
_main/_base_structure/domain/__pycache__/__init__.cpython-310.pyc
_main/_base_structure/domain/__pycache__/example.cpython-310.pyc
_main/_base_structure/features/example/__init__.py
_main/_base_structure/features/example/dependency.json
_main/_base_structure/features/example/http_service_flask.py
_main/_base_structure/features/example/repository_mysql.py
_main/_base_structure/features/example/usecase_v1.py
_main/_base_structure/features/example/__pycache__/__init__.cpython-310.pyc
_main/_base_structure/features/example/__pycache__/http_service_flask.cpython-310.pyc
_main/_base_structure/features/example/__pycache__/repository_mysql.cpython-310.pyc
_main/_base_structure/features/example/__pycache__/usecase_v1.cpython-310.pyc
_main/_base_structure/infra/build.sh
_main/_base_structure/infra/chmod.sh
_main/_base_structure/infra/docker-down.sh
_main/_base_structure/infra/docker-stop.sh
_main/_base_structure/infra/docker-up.sh
_main/_base_structure/infra/start.sh
ayapingping_py-4.6.3.dist-info/LICENSE
ayapingping_py-4.6.3.dist-info/METADATA
ayapingping_py-4.6.3.dist-info/WHEEL
ayapingping_py-4.6.3.dist-info/entry_points.txt
ayapingping_py-4.6.3.dist-info/top_level.txt
ayapingping_py-4.6.3.dist-info/RECORD
