Metadata-Version: 2.1
Name: ayapingping-py
Version: 4.6.3
Summary: ayapingping-py generates standard project structure to build applications in Python that follow Clean Architecture and Feature-Driven Design concept
Home-page: UNKNOWN
Author: Dali Kewara
Author-email: dalikewara@gmail.com
License: MIT
Keywords: python,ayapingping,ayapingping-py,framework,structure,design,feature,project,clean-architecture,feature-driven-design,domain-driven-design
Platform: UNKNOWN
Classifier: Programming Language :: Python :: 3
Classifier: License :: OSI Approved :: MIT License
Classifier: Operating System :: OS Independent
Requires-Python: >=3.10.12
License-File: LICENSE
